unwind/__init__.py
unwind/main.py
unwind/typing.py
unwind-0.3.1.dist-info/LICENSE
unwind-0.3.1.dist-info/METADATA
unwind-0.3.1.dist-info/WHEEL
unwind-0.3.1.dist-info/top_level.txt
unwind-0.3.1.dist-info/RECORD
