Metadata-Version: 2.1
Name: unwind
Version: 0.3.1
Summary: A simple solution to analysis and extract information from traceback.
Home-page: https://github.com/GraiaCommunity/Unwind
Author: RF-Tar-Railt
Author-email: rf_tar_railt@qq.com
License: MIT
Project-URL: Bug Reports, https://github.com/GraiaCommunity/Unwind/issues
Project-URL: Source, https://github.com/GraiaCommunity/Unwind
Keywords: traceback,exception,crash-report
Platform: UNKNOWN
Classifier: Development Status :: 4 - Beta
Classifier: License :: OSI Approved :: MIT License
Classifier: Programming Language :: Python :: 3.8
Classifier: Programming Language :: Python :: 3.9
Classifier: Programming Language :: Python :: 3.10
Classifier: Programming Language :: Python :: 3.11
Classifier: Operating System :: OS Independent
Requires-Python: >=3.8
License-File: LICENSE
